huskium/__init__.py
huskium/common.py
huskium/dynamic.py
huskium/exception.py
huskium/logging.py
huskium/types.py
huskium/wait.py
huskium/appium/__init__.py
huskium/appium/by.py
huskium/appium/ecex.py
huskium/appium/element.py
huskium/appium/elements.py
huskium/appium/page.py
huskium/selenium/__init__.py
huskium/selenium/by.py
huskium/selenium/ecex.py
huskium/selenium/element.py
huskium/selenium/elements.py
huskium/selenium/page.py
huskium-1.2.0.dist-info/licenses/LICENSE
huskium-1.2.0.dist-info/METADATA
huskium-1.2.0.dist-info/WHEEL
huskium-1.2.0.dist-info/top_level.txt
huskium-1.2.0.dist-info/RECORD
