Metadata-Version: 2.4
Name: huskium
Version: 1.2.0
Summary: UI Automation Page Objects design pattern.
Author-email: Johnny <johnny071531@gmail.com>
License: MIT
Project-URL: Homepage, https://github.com/uujohnnyuu/huskium
Keywords: huskium,huskypo,selenium,appium,page object,automation
Requires-Python: >=3.12
License-File: LICENSE
Requires-Dist: Appium-Python-Client>=5.0.0
Dynamic: license-file
